fabulous_cli/__init__.py
fabulous_cli/cli.py
fabulous_cli-0.1.0.dist-info/LICENSE
fabulous_cli-0.1.0.dist-info/METADATA
fabulous_cli-0.1.0.dist-info/WHEEL
fabulous_cli-0.1.0.dist-info/entry_points.txt
fabulous_cli-0.1.0.dist-info/top_level.txt
fabulous_cli-0.1.0.dist-info/RECORD
