Metadata-Version: 2.2
Name: fabulous-cli
Version: 0.1.0
Summary: Fabulous CLI - A basic Python CLI example
Author-email: Your Name <your.email@example.com>
Project-URL: Homepage, https://github.com/yourusername/fabulous-cli
Classifier: Programming Language :: Python :: 3
Classifier: License :: OSI Approved :: MIT License
Classifier: Operating System :: OS Independent
Requires-Python: >=3.6
License-File: LICENSE
